skimtoken-0.2.2.dist-info/METADATA
skimtoken-0.2.2.dist-info/WHEEL
skimtoken-0.2.2.dist-info/entry_points.txt
skimtoken-0.2.2.dist-info/licenses/LICENSE
skimtoken/__init__.py
skimtoken/__init__.pyi
skimtoken/_skimtoken_core.abi3.so
skimtoken/basic.py
skimtoken/basic.pyi
skimtoken/multilingual.py
skimtoken/multilingual.pyi
skimtoken/multilingual_simple.py
skimtoken/multilingual_simple.pyi
skimtoken/simple.py
skimtoken/simple.pyi
skimtoken-0.2.2.dist-info/RECORD
