Metadata-Version: 2.4
Name: skimtoken
Version: 0.2.2
License-File: LICENSE
Summary: Fast token count estimation library
Home-Page: https://github.com/masaishi/skimtoken
Author: masaishi <mwishiha@ucsc.edu>
Author-email: masaishi <mwishiha@ucsc.edu>
License: MIT
Requires-Python: >=3.9
Project-URL: Source Code, https://github.com/masaishi/skimtoken
